drawcustom/__init__.py
drawcustom/colors.py
drawcustom/coordinates.py
drawcustom/core.py
drawcustom/fonts.py
drawcustom/media_loader.py
drawcustom/registry.py
drawcustom/types.py
drawcustom/assets/ppb.ttf
drawcustom/assets/rbm.ttf
drawcustom/elements/__init__.py
drawcustom/elements/debug.py
drawcustom/elements/icons.py
drawcustom/elements/media.py
drawcustom/elements/shapes.py
drawcustom/elements/text.py
drawcustom/elements/visualizations.py
drawcustom-0.2.0.dist-info/METADATA
drawcustom-0.2.0.dist-info/WHEEL
drawcustom-0.2.0.dist-info/licenses/LICENSE
drawcustom-0.2.0.dist-info/RECORD
