Metadata-Version: 2.4
Name: drawcustom
Version: 0.2.0
Summary: Pure image rendering from drawing instructions for e-paper displays
Project-URL: Homepage, https://github.com/g4bri3lDev/drawcustom
Project-URL: Repository, https://github.com/g4bri3lDev/drawcustom
Project-URL: Issues, https://github.com/g4bri3lDev/drawcustom/issues
Author-email: g4bri3lDev <admin@g4bri3l.de>
License: MIT
License-File: LICENSE
Keywords: drawcustom,e-paper,eink,image,rendering
Classifier: Development Status :: 3 - Alpha
Classifier: Intended Audience :: Developers
Classifier: License :: OSI Approved :: MIT License
Classifier: Programming Language :: Python :: 3
Classifier: Programming Language :: Python :: 3.11
Classifier: Programming Language :: Python :: 3.12
Classifier: Programming Language :: Python :: 3.13
Classifier: Topic :: Software Development :: Libraries :: Python Modules
Requires-Python: >=3.11
Requires-Dist: aiohttp>=3.8.0
Requires-Dist: pillow>=10.0.0
Requires-Dist: pytest>=9.0.2
Requires-Dist: qrcode[pil]>=7.4.2
Requires-Dist: resize-image>=0.4.0
Provides-Extra: dev
Requires-Dist: mypy>=1.19.1; extra == 'dev'
Requires-Dist: ruff>=0.14.10; extra == 'dev'
Provides-Extra: property
Requires-Dist: hypothesis>=6.148.8; extra == 'property'
Provides-Extra: test
Requires-Dist: pytest-asyncio>=1.3.0; extra == 'test'
Requires-Dist: pytest-cov>=7.0.0; extra == 'test'
Requires-Dist: pytest-xdist>=3.8.0; extra == 'test'
Requires-Dist: pytest>=9.0.2; extra == 'test'
Provides-Extra: visual
Requires-Dist: imagehash>=4.3.2; extra == 'visual'
Requires-Dist: syrupy>=5.0.0; extra == 'visual'
